pgx_minatar/__init__.py
pgx_minatar/asterix.py
pgx_minatar/breakout.py
pgx_minatar/freeway.py
pgx_minatar/seaquest.py
pgx_minatar/space_invaders.py
pgx_minatar/utils.py
tests/__init__.py
tests/minatar_utils.py
tests/test_asterix.py
tests/test_breakout.py
tests/test_freeway.py
tests/test_seaquest.py
tests/test_space_invaders.py
pgx_minatar-0.5.1.dist-info/LICENSE
pgx_minatar-0.5.1.dist-info/METADATA
pgx_minatar-0.5.1.dist-info/WHEEL
pgx_minatar-0.5.1.dist-info/top_level.txt
pgx_minatar-0.5.1.dist-info/RECORD
