Metadata-Version: 2.1
Name: pgx-minatar
Version: 0.5.1
Summary: MinAtar extension for Pgx
Home-page: https://github.com/sotetsuk/pgx-minatar
Author: Sotetsu KOYAMADA
Author-email: sotetsu.koyamada@gmail.com
Classifier: Programming Language :: Python :: 3.8
Classifier: Programming Language :: Python :: 3.9
Classifier: Programming Language :: Python :: 3.10
Classifier: Programming Language :: Python :: 3.11
Classifier: Programming Language :: Python :: 3.12
License-File: LICENSE
